sailhouse/__init__.py
sailhouse/client.py
sailhouse/exceptions.py
sailhouse-0.1.1.dist-info/METADATA
sailhouse-0.1.1.dist-info/WHEEL
sailhouse-0.1.1.dist-info/licenses/LICENSE
sailhouse-0.1.1.dist-info/RECORD
