Metadata-Version: 2.4
Name: sailhouse
Version: 0.1.1
Summary: Python SDK for Sailhouse - Event Streaming Platform
Project-URL: Homepage, https://github.com/sailhouse/sdk-python
Project-URL: Documentation, https://docs.sailhouse.dev/
Project-URL: Repository, https://github.com/sailhouse/sdk-python.git
Project-URL: Bug Tracker, https://github.com/sailhouse/sdk-python/issues
Author-email: Ed Stephinson <ed@sailhouse.dev>
License: MIT License
License-File: LICENSE
Keywords: events,pubsub,sailhouse,streaming
Classifier: Development Status :: 4 - Beta
Classifier: Intended Audience :: Developers
Classifier: License :: OSI Approved :: MIT License
Classifier: Operating System :: OS Independent
Classifier: Programming Language :: Python :: 3
Classifier: Programming Language :: Python :: 3.8
Classifier: Programming Language :: Python :: 3.9
Classifier: Programming Language :: Python :: 3.10
Classifier: Programming Language :: Python :: 3.11
Classifier: Topic :: Software Development :: Libraries :: Python Modules
Requires-Python: >=3.8
Requires-Dist: requests>=2.28.0
Requires-Dist: typing-extensions>=4.0.0
Requires-Dist: websockets>=10.0
Provides-Extra: dev
Requires-Dist: pytest-asyncio; extra == 'dev'
Requires-Dist: pytest-cov; extra == 'dev'
Requires-Dist: pytest>=6.0; extra == 'dev'
Requires-Dist: requests-mock; extra == 'dev'
